preparenovonix/__init__.py
preparenovonix/compare.py
preparenovonix/novonix_add.py
preparenovonix/novonix_clean.py
preparenovonix/novonix_io.py
preparenovonix/novonix_prep.py
preparenovonix/novonix_variables.py
preparenovonix/test_compare.py
preparenovonix/test_novonix_add.py
preparenovonix/test_novonix_clean.py
preparenovonix/test_novonix_io.py
preparenovonix/test_prep.py
pycode/__init__.py
pycode/novonix_add.py
preparenovonix-1.0.3.dist-info/LICENSE
preparenovonix-1.0.3.dist-info/METADATA
preparenovonix-1.0.3.dist-info/WHEEL
preparenovonix-1.0.3.dist-info/top_level.txt
preparenovonix-1.0.3.dist-info/RECORD
