Metadata-Version: 2.1
Name: preparenovonix
Version: 1.0.3
Summary: Clean and add extra information to data produced by the battery cyclers from Novonix.
Home-page: https://github.com/BatLabLancaster/preparenovonix
License: MIT
Platform: UNKNOWN
Classifier: Programming Language :: Python :: 3
Classifier: License :: OSI Approved :: MIT License
Classifier: Operating System :: OS Independent
Requires-Dist: numpy (>=1.15)
Requires-Dist: matplotlib (>=3.0)
